{
  "project_info": {
    "project_number": "51570413013",
    "project_id": "fir-testing-4647b",
    "storage_bucket": "fir-testing-4647b.appspot.com"
  },
  "client": [
    {
      "client_info": {
        "mobilesdk_app_id": "1:51570413013:android:0f7479f41c79428748c15c",
        "android_client_info": {
          "package_name": "com.example.test_firestore"
        }
      },
      "oauth_client": [
        {
          "client_id": "51570413013-7fcetpial28bi5phvb0p9o9l4ktnf9ai.apps.googleusercontent.com",
          "client_type": 3
        }
      ],
      "api_key": [
        {
          "current_key": "AIzaSyBHfu2FvTBg_rueXscf0oZMtECBYC7uzuc"
        }
      ],
      "services": {
        "appinvite_service": {
          "other_platform_oauth_client": [
            {
              "client_id": "51570413013-7fcetpial28bi5phvb0p9o9l4ktnf9ai.apps.googleusercontent.com",
              "client_type": 3
            }
          ]
        }
      }
    }
  ],
  "configuration_version": "1"
}